[
  {
    "videoGrup": "ElektraWeb",
    "videos": [
      {
        "videoName": "ElektraWeb - Raporlar - Eda Yılmaz",
        "videoDescription":"",
        "youtubeVideoID": "_cmwZI-5YMs", 
        "videoTime": "84:20",
        "videoIntTime": 84.20
      }
    ]
  },
  {
    "videoGrup": "Test",
    "videos": [
      {
        "videoName": "Test1",
        "videoDescription": "",
        "youtubeVideoID": "rl_c_vGQcDs",
        "videoTime": "3:54",
        "videoIntTime": 3.54
      },
      {
        "videoName": "Test2",
        "videoDescription": "",
        "youtubeVideoID": "86tNjQByVO0",
        "videoTime": "1:13",
        "videoIntTime": 1.13
      }
    ]
  }]
  
